<?xml version="1.0" encoding="utf-8"?>
<FacturaXML xmlns:xsi="http://www.w3.org/2001/XMLSchema-instance" xmlns:xsd="http://www.w3.org/2001/XMLSchema">
  <items>
    <FacturaItemXML>
      <Descripcion>BATIDORA LICUAD MIXER PHILIPS HR1363/06</Descripcion>
      <Cantidad>1</Cantidad>
      <PrecioUnitario>1.00</PrecioUnitario>
      <AlicuotaIva>0.00</AlicuotaIva>
      <ImpuestosInternos>0.00</ImpuestosInternos>
      <Descuento>0</Descuento>
    </FacturaItemXML>
  </items>
  <TipoFactura>Factura A</TipoFactura>
  <Comprador>Cliente Prueba Codigo</Comprador>
  <Cuit>20184262984</Cuit>
  <TipoIva>Consumidor Final</TipoIva>
  <FormaPago>Cuenta Corriente</FormaPago>
  <Total>0</Total>
  <TotalPercepcion>0</TotalPercepcion>
  <PorcPercepcion>0</PorcPercepcion>
  <Descuento>0</Descuento>
</FacturaXML>